QuantumRingsLib.cp314-win_amd64.pyd
quantumrings_cuda12x-0.11.2314.dist-info/licenses/LICENSE.rst
quantumrings_cuda12x-0.11.2314.dist-info/METADATA
quantumrings_cuda12x-0.11.2314.dist-info/WHEEL
quantumrings_cuda12x-0.11.2314.dist-info/top_level.txt
quantumrings_cuda12x-0.11.2314.dist-info/RECORD
