Metadata-Version: 2.4
Name: quantumrings-cuda12x
Version: 0.11.2314
Summary: A Quantum Development Library
Author-email: "Quantum Rings Inc." <contact@quantumrings.com>
Project-URL: Homepage, https://www.quantumrings.com
Project-URL: Documentation, https://portal.quantumrings.com/doc/
Project-URL: API Reference, https://portal.quantumrings.com/doc/modules.html
Keywords: quantum,quantum circuit,quantum computing,quantum programming language,quantum register,quantum tools,tools,sdk
Classifier: Development Status :: 4 - Beta
Classifier: Environment :: Console
Classifier: Intended Audience :: Developers
Classifier: Intended Audience :: Science/Research
Classifier: Topic :: Software Development :: Build Tools
Classifier: Topic :: Scientific/Engineering
Classifier: Programming Language :: Python :: 3.14
Classifier: Operating System :: Microsoft :: Windows
Requires-Python: ==3.14.*
License-File: LICENSE.rst
Dynamic: license-file
Dynamic: requires-python
